.coveragerc
.gitignore
.travis.yml
.zerotk.uniform.yml
LICENSE.txt
README.md
appveyor.yml
pytest.ini
requirements.txt
setup.cfg
setup.py
tasks.py
tests/conftest.py
tests/easyfs_test.py
tests/easyfs_test/file.txt
tests/easyfs_test/net_use.txt
tests/easyfs_test/complex_tree/1
tests/easyfs_test/complex_tree/2
tests/easyfs_test/complex_tree/subdir_1/subsubdir_1/1.1.1
tests/easyfs_test/complex_tree/subdir_1/subsubdir_1/1.1.2
tests/easyfs_test/complex_tree/subdir_2/2.1
tests/easyfs_test/files/source/alpha.txt
tests/easyfs_test/files/source/bravo.txt
tests/easyfs_test/files/source/subfolder/subfile.txt
tests/easyfs_test/md5/file
tests/easyfs_test/md5/file.md5
zerotk/__init__.py
zerotk.easyfs.egg-info/PKG-INFO
zerotk.easyfs.egg-info/SOURCES.txt
zerotk.easyfs.egg-info/dependency_links.txt
zerotk.easyfs.egg-info/namespace_packages.txt
zerotk.easyfs.egg-info/requires.txt
zerotk.easyfs.egg-info/top_level.txt
zerotk/easyfs/__init__.py
zerotk/easyfs/_easyfs.py
zerotk/easyfs/_easyfs_win32.py
zerotk/easyfs/_exceptions.py
zerotk/easyfs/fixtures.py