Metadata-Version: 1.1
Name: zerotk.easyfs
Version: 1.0.3
Summary: File system utilities for python.
Home-page: https://github.com/zerotk/easyfs
Author: Alexandre Andrade
Author-email: kaniabi@gmail.com
License: UNKNOWN
Keywords: filesystem,symlink,windows,readlink,islink
Platform: UNKNOWN
Classifier: Development Status :: 5 - Production/Stable
Classifier: Intended Audience :: Developers
Classifier: Topic :: Software Development :: Libraries :: Python Modules
Classifier: License :: OSI Approved :: GNU General Public License v3 (GPLv3)
Classifier: Programming Language :: Python :: 2
Classifier: Programming Language :: Python :: 2.7
Classifier: Programming Language :: Python :: 3
Classifier: Programming Language :: Python :: 3.5
